customer_report/__init__.py
customer_report/__main__.py
customer_report/report.py
customer_report_owttsair-0.1.0.dist-info/METADATA
customer_report_owttsair-0.1.0.dist-info/WHEEL
customer_report_owttsair-0.1.0.dist-info/top_level.txt
customer_report_owttsair-0.1.0.dist-info/RECORD
